LICENSE
MANIFEST.in
README.md
requirements.txt
setup.py
NSoL.egg-info/PKG-INFO
NSoL.egg-info/SOURCES.txt
NSoL.egg-info/dependency_links.txt
NSoL.egg-info/entry_points.txt
NSoL.egg-info/not-zip-safe
NSoL.egg-info/requires.txt
NSoL.egg-info/top_level.txt
nsol/__about__.py
nsol/__init__.py
nsol/admm_linear_solver.py
nsol/admm_linear_solver_parameter_study.py
nsol/data_reader.py
nsol/data_writer.py
nsol/deconvolution_solver_parameter_study_interface.py
nsol/definitions.py
nsol/input_argparser.py
nsol/kernels.py
nsol/linear_operators.py
nsol/linear_solver.py
nsol/loss_functions.py
nsol/noise.py
nsol/observer.py
nsol/optimize.py
nsol/parameter_study.py
nsol/primal_dual_solver.py
nsol/primal_dual_solver_parameter_study.py
nsol/principal_component_analysis.py
nsol/prior_measures.py
nsol/proximal_operators.py
nsol/reader_parameter_study.py
nsol/similarity_measures.py
nsol/solver.py
nsol/solver_parameter_study.py
nsol/tikhonov_linear_solver.py
nsol/tikhonov_linear_solver_parameter_study.py
nsol/application/__init__.py
nsol/application/corrupt_data.py
nsol/application/run_deconvolution.py
nsol/application/run_deconvolution_study.py
nsol/application/run_denoising.py
nsol/application/run_denoising_study.py
nsol/application/show_parameter_study.py
tests/__init__.py
tests/kernels_test.py
tests/loss_functions_test.py
tests/run_deconvolution_study_test.py
tests/run_deconvolution_test.py
tests/run_denoising_study_test.py
tests/run_denoising_test.py
tests/run_tests.py
tests/similarity_measures_test.py
tests/solvers_test.py