Metadata-Version: 2.1
Name: NSoL
Version: 0.1.12
Summary: The Numerical Solver Library (NSoL) is a research-focused toolkit for denoising and deconvolution applications using ADMM and Primal-Dual methods.
Home-page: https://github.com/gift-surg/NSoL
Author: Michael Ebner
Author-email: michael.ebner.14@ucl.ac.uk
License: BSD-3-Clause
Keywords: development numericalsolver convexoptimisation
Platform: UNKNOWN
Classifier: Intended Audience :: Developers
Classifier: Intended Audience :: Healthcare Industry
Classifier: Intended Audience :: Science/Research
Classifier: License :: OSI Approved :: BSD License
Classifier: Topic :: Software Development :: Build Tools
Classifier: Topic :: Scientific/Engineering :: Medical Science Apps.
Classifier: Programming Language :: Python
Classifier: Programming Language :: Python :: 2
Classifier: Programming Language :: Python :: 3
